{
  "fire-fighting": {
    "filters": [
      "All Products",
      "Pumps",
      "Sprinkler",
      "Valves",
      "Hydrant",
      "Cabinets",
      "Pipes",
      "Gases"
    ],
    "groups": [
      {
        "n": 1,
        "title": "Fire Pump Sets",
        "desc": "",
        "cta": "Request a Quotation",
        "items": [
          {
            "name": "Fire Pump Sets",
            "icon": "pump"
          }
        ]
      },
      {
        "n": 2,
        "title": "Sprinkler Systems",
        "desc": "",
        "cta": "Request a Quotation",
        "items": [
          {
            "name": "Upright Sprinkler",
            "icon": "sprinkler"
          },
          {
            "name": "Pendent Sprinkler",
            "icon": "sprinkler"
          },
          {
            "name": "Sidewall Sprinkler",
            "icon": "sprinkler"
          },
          {
            "name": "Concealed Sprinkler",
            "icon": "sprinkler"
          },
          {
            "name": "Flexible Sprinkler Hose",
            "icon": "sprinkler"
          },
          {
            "name": "Sprinkler Guard",
            "icon": "sprinkler"
          },
          {
            "name": "Escutcheon",
            "icon": "box"
          }
        ]
      },
      {
        "n": 3,
        "title": "Fire Fighting Valves & Control",
        "desc": "",
        "cta": "Request a Quotation",
        "items": [
          {
            "name": "Alarm Check Valve",
            "icon": "valve"
          },
          {
            "name": "Deluge Valve",
            "icon": "valve"
          },
          {
            "name": "Pre-Action Valve",
            "icon": "valve"
          },
          {
            "name": "Zone Control Valve",
            "icon": "valve"
          },
          {
            "name": "Test And Drain Valve",
            "icon": "valve"
          },
          {
            "name": "Water Motor Gong",
            "icon": "gauge"
          },
          {
            "name": "OS&Y Valve Flanged",
            "icon": "coupling"
          }
        ]
      },
      {
        "n": 4,
        "title": "Supervision Devices",
        "desc": "",
        "cta": "Request a Quotation",
        "items": [
          {
            "name": "Flow Switch",
            "icon": "gauge"
          },
          {
            "name": "Tamper Switch",
            "icon": "gauge"
          },
          {
            "name": "Pressure Switch",
            "icon": "gauge"
          }
        ]
      },
      {
        "n": 5,
        "title": "Hydrant Systems",
        "desc": "",
        "cta": "Request a Quotation",
        "items": [
          {
            "name": "Pillar Hydrant",
            "icon": "hydrant"
          },
          {
            "name": "Wet Barrel Hydrant",
            "icon": "hydrant"
          },
          {
            "name": "Dry Barrel Hydrant",
            "icon": "hydrant"
          },
          {
            "name": "Underground Hydrant",
            "icon": "hydrant"
          },
          {
            "name": "Hydrant Valve",
            "icon": "hydrant"
          },
          {
            "name": "Hydrant Cap",
            "icon": "hydrant"
          },
          {
            "name": "Hydrant Wrench",
            "icon": "hydrant"
          }
        ]
      },
      {
        "n": 6,
        "title": "Fire Cabinets & Hose Systems",
        "desc": "",
        "cta": "Request a Quotation",
        "items": [
          {
            "name": "Fire Hose Cabinet",
            "icon": "cabinet"
          },
          {
            "name": "Hose Reel",
            "icon": "reel"
          },
          {
            "name": "Fire Hose",
            "icon": "reel"
          },
          {
            "name": "Landing Valve",
            "icon": "valve"
          },
          {
            "name": "Angle Valve",
            "icon": "valve"
          },
          {
            "name": "Branch Pipe",
            "icon": "droplets"
          },
          {
            "name": "Nozzle",
            "icon": "droplets"
          },
          {
            "name": "Hose Rack",
            "icon": "reel"
          },
          {
            "name": "Single Fire Hose Cabinet FHC-Class1&2",
            "icon": "cabinet"
          }
        ]
      },
      {
        "n": 7,
        "title": "Breeching & Fire Department Connections",
        "desc": "",
        "cta": "Request a Quotation",
        "items": [
          {
            "name": "Breeching Inlet",
            "icon": "coupling"
          },
          {
            "name": "Fire Department Connection",
            "icon": "coupling"
          },
          {
            "name": "Inlet Valve",
            "icon": "coupling"
          },
          {
            "name": "Caps",
            "icon": "box"
          },
          {
            "name": "Chains",
            "icon": "box"
          },
          {
            "name": "Breeching Connection",
            "icon": "coupling"
          }
        ]
      },
      {
        "n": 8,
        "title": "Pipes & Fittings",
        "desc": "",
        "cta": "Request a Quotation",
        "items": [
          {
            "name": "Steel Pipe",
            "icon": "pipe"
          },
          {
            "name": "CPVC Pipe",
            "icon": "pipe"
          },
          {
            "name": "HDPE Pipe",
            "icon": "pipe"
          },
          {
            "name": "Grooved Fittings",
            "icon": "coupling"
          },
          {
            "name": "Threaded Fittings",
            "icon": "coupling"
          },
          {
            "name": "Flanged Fittings",
            "icon": "coupling"
          },
          {
            "name": "Welded Fittings",
            "icon": "coupling"
          },
          {
            "name": "Seamless Pipes",
            "icon": "pipe"
          },
          {
            "name": "Threaded Fitting",
            "icon": "coupling"
          }
        ]
      },
      {
        "n": 9,
        "title": "Gases & Special Suppression Systems",
        "desc": "",
        "cta": "Request a Quotation",
        "items": [
          {
            "name": "FM-200",
            "icon": "spray"
          },
          {
            "name": "CO2 Systems",
            "icon": "spray"
          },
          {
            "name": "Foam Systems",
            "icon": "spray"
          },
          {
            "name": "Kitchen Hood Suppression",
            "icon": "flame"
          },
          {
            "name": "Aerosol system",
            "icon": "spray"
          }
        ]
      }
    ],
    "featured": [
      {
        "name": "Upright sprinkler",
        "spec": "",
        "icon": "sprinkler",
        "image": "/images/p-upright-sprinkler.jpg"
      },
      {
        "name": "Sprinkler System — Ref 41",
        "spec": "للحصول على هذا المنتج، الرجاء التواصل مع المورد",
        "icon": "sprinkler",
        "image": "/images/p-sprinkler-system-ref-41.jpg"
      },
      {
        "name": "Sprinkler System — Ref 42",
        "spec": "للحصول على هذا المنتج، الرجاء التواصل مع المورد",
        "icon": "sprinkler",
        "image": "/images/p-sprinkler-system-ref-42.jpg"
      },
      {
        "name": "Sprinkler System — Ref 43",
        "spec": "للحصول على هذا المنتج، الرجاء التواصل مع المورد",
        "icon": "sprinkler",
        "image": "/images/p-sprinkler-system-ref-43.jpg"
      },
      {
        "name": "OS&Y Valve Flanged",
        "spec": "",
        "icon": "coupling",
        "image": "/images/p-osy-valve-flanged.jpg"
      },
      {
        "name": "Fire Fighting Valve & Control — Ref 103",
        "spec": "للحصول على هذا المنتج، الرجاء التواصل مع المورد",
        "icon": "valve",
        "image": "/images/p-fire-fighting-valve-control-ref-103.jpg"
      },
      {
        "name": "Fire Fighting Valve & Control — Ref 37",
        "spec": "للحصول على هذا المنتج، الرجاء التواصل مع المورد",
        "icon": "valve",
        "image": "/images/p-fire-fighting-valve-control-ref-37.jpg"
      },
      {
        "name": "Fire Fighting Valve & Control — Ref 3",
        "spec": "للحصول على هذا المنتج، الرجاء التواصل مع المورد",
        "icon": "valve",
        "image": "/images/p-fire-fighting-valve-control-ref-3.jpg"
      },
      {
        "name": "Fire Fighting Valve & Control — Ref 104",
        "spec": "للحصول على هذا المنتج، الرجاء التواصل مع المورد",
        "icon": "valve",
        "image": "/images/p-fire-fighting-valve-control-ref-104.jpg"
      },
      {
        "name": "Fire Fighting Valve & Control — Ref 38",
        "spec": "للحصول على هذا المنتج، الرجاء التواصل مع المورد",
        "icon": "valve",
        "image": "/images/p-fire-fighting-valve-control-ref-38.jpg"
      },
      {
        "name": "Fire Fighting Valve & Control — Ref 31",
        "spec": "للحصول على هذا المنتج، الرجاء التواصل مع المورد",
        "icon": "valve",
        "image": "/images/p-fire-fighting-valve-control-ref-31.jpg"
      },
      {
        "name": "Fire Fighting Valve & Control — Ref 45",
        "spec": "للحصول على هذا المنتج، الرجاء التواصل مع المورد",
        "icon": "valve",
        "image": "/images/p-fire-fighting-valve-control-ref-45.jpg"
      },
      {
        "name": "Fire Fighting Valve & Control — Ref 39",
        "spec": "للحصول على هذا المنتج، الرجاء التواصل مع المورد",
        "icon": "valve",
        "image": "/images/p-fire-fighting-valve-control-ref-39.jpg"
      },
      {
        "name": "Flow switch",
        "spec": "",
        "icon": "gauge",
        "image": "/images/p-flow-switch.jpg"
      },
      {
        "name": "Supervision Device — Ref 33",
        "spec": "للحصول على هذا المنتج، الرجاء التواصل مع المورد",
        "icon": "gauge",
        "image": "/images/p-supervision-device-ref-33.jpg"
      },
      {
        "name": "Supervision Device — Ref 32",
        "spec": "للحصول على هذا المنتج، الرجاء التواصل مع المورد",
        "icon": "gauge",
        "image": "/images/p-supervision-device-ref-32.jpg"
      },
      {
        "name": "dry barrel hydrant",
        "spec": "",
        "icon": "hydrant",
        "image": "/images/p-dry-barrel-hydrant.jpg"
      },
      {
        "name": "Hydrant System — Ref 46",
        "spec": "للحصول على هذا المنتج، الرجاء التواصل مع المورد",
        "icon": "hydrant",
        "image": "/images/p-hydrant-system-ref-46.jpg"
      },
      {
        "name": "Hydrant System — Ref 47",
        "spec": "للحصول على هذا المنتج، الرجاء التواصل مع المورد",
        "icon": "hydrant",
        "image": "/images/p-hydrant-system-ref-47.jpg"
      },
      {
        "name": "Hydrant System — Ref 36",
        "spec": "للحصول على هذا المنتج، الرجاء التواصل مع المورد",
        "icon": "hydrant",
        "image": "/images/p-hydrant-system-ref-36.jpg"
      },
      {
        "name": "Hydrant System — Ref 48",
        "spec": "للحصول على هذا المنتج، الرجاء التواصل مع المورد",
        "icon": "hydrant",
        "image": "/images/p-hydrant-system-ref-48.jpg"
      },
      {
        "name": "Single Fire Hose Cabinet FHC-Class1&2",
        "spec": "",
        "icon": "cabinet",
        "image": "/images/p-single-fire-hose-cabinet-fhc-class12.jpg"
      },
      {
        "name": "Fire Cabinet & Hose System — Ref 90",
        "spec": "للحصول على هذا المنتج، الرجاء التواصل مع المورد",
        "icon": "cabinet",
        "image": "/images/p-fire-cabinet-hose-system-ref-90.jpg"
      },
      {
        "name": "Fire Cabinet & Hose System — Ref 51",
        "spec": "للحصول على هذا المنتج، الرجاء التواصل مع المورد",
        "icon": "cabinet",
        "image": "/images/p-fire-cabinet-hose-system-ref-51.jpg"
      },
      {
        "name": "Fire Cabinet & Hose System — Ref 52",
        "spec": "للحصول على هذا المنتج، الرجاء التواصل مع المورد",
        "icon": "cabinet",
        "image": "/images/p-fire-cabinet-hose-system-ref-52.jpg"
      },
      {
        "name": "Fire Cabinet & Hose System — Ref 96",
        "spec": "للحصول على هذا المنتج، الرجاء التواصل مع المورد",
        "icon": "cabinet",
        "image": "/images/p-fire-cabinet-hose-system-ref-96.jpg"
      },
      {
        "name": "Fire Cabinet & Hose System — Ref 97",
        "spec": "للحصول على هذا المنتج، الرجاء التواصل مع المورد",
        "icon": "cabinet",
        "image": "/images/p-fire-cabinet-hose-system-ref-97.jpg"
      },
      {
        "name": "Fire Cabinet & Hose System — Ref 98",
        "spec": "للحصول على هذا المنتج، الرجاء التواصل مع المورد",
        "icon": "cabinet",
        "image": "/images/p-fire-cabinet-hose-system-ref-98.jpg"
      },
      {
        "name": "Fire Cabinet & Hose System — Ref 53",
        "spec": "للحصول على هذا المنتج، الرجاء التواصل مع المورد",
        "icon": "cabinet",
        "image": "/images/p-fire-cabinet-hose-system-ref-53.jpg"
      },
      {
        "name": "Fire Cabinet & Hose System — Ref 54",
        "spec": "للحصول على هذا المنتج، الرجاء التواصل مع المورد",
        "icon": "cabinet",
        "image": "/images/p-fire-cabinet-hose-system-ref-54.jpg"
      },
      {
        "name": "Fire Cabinet & Hose System — Ref 55",
        "spec": "للحصول على هذا المنتج، الرجاء التواصل مع المورد",
        "icon": "cabinet",
        "image": "/images/p-fire-cabinet-hose-system-ref-55.jpg"
      },
      {
        "name": "Breeching Connection",
        "spec": "",
        "icon": "coupling",
        "image": "/images/p-breeching-connection.jpg"
      },
      {
        "name": "Breeching & Fire Department Connection — Ref 50",
        "spec": "للحصول على هذا المنتج، الرجاء التواصل مع المورد",
        "icon": "coupling",
        "image": "/images/p-breeching-fire-department-connection-ref-50.jpg"
      },
      {
        "name": "Seamless Pipes",
        "spec": "",
        "icon": "pipe",
        "image": "/images/p-seamless-pipes.jpg"
      },
      {
        "name": "Pipes & Fitting — Ref 81",
        "spec": "للحصول على هذا المنتج، الرجاء التواصل مع المورد",
        "icon": "pipe",
        "image": "/images/p-pipes-fitting-ref-81.jpg"
      },
      {
        "name": "Pipes & Fitting — Ref 62",
        "spec": "للحصول على هذا المنتج، الرجاء التواصل مع المورد",
        "icon": "pipe",
        "image": "/images/p-pipes-fitting-ref-62.jpg"
      },
      {
        "name": "Threaded Fitting",
        "spec": "",
        "icon": "coupling",
        "image": "/images/p-threaded-fitting.jpg"
      },
      {
        "name": "FM-200",
        "spec": "",
        "icon": "spray",
        "image": "/images/p-fm-200.jpg"
      },
      {
        "name": "CO2 Systems",
        "spec": "",
        "icon": "spray",
        "image": "/images/p-co2-systems.jpg"
      },
      {
        "name": "Foam Systems",
        "spec": "",
        "icon": "spray",
        "image": "/images/p-foam-systems.jpg"
      },
      {
        "name": "Kitchen Hood Suppression",
        "spec": "",
        "icon": "flame",
        "image": "/images/p-kitchen-hood-suppression.jpg"
      },
      {
        "name": "Aerosol system",
        "spec": "",
        "icon": "spray",
        "image": "/images/p-aerosol-system.jpg"
      }
    ]
  },
  "fire-alarm": {
    "filters": [
      "All Products"
    ],
    "groups": [
      {
        "n": 1,
        "title": "Fire Alarm Systems",
        "desc": "",
        "cta": "Request a Quotation",
        "items": [
          {
            "name": "Fire Alarm Systems",
            "icon": "bell"
          }
        ]
      }
    ],
    "featured": [
      {
        "name": "Fire Alarm System",
        "spec": "للحصول على هذا المنتج، الرجاء التواصل مع المورد",
        "icon": "bell",
        "image": "/images/p-fire-alarm-system.jpg"
      }
    ]
  },
  "water-network": {
    "filters": [
      "All Products",
      "Valves",
      "Strainers",
      "Fittings",
      "Covers"
    ],
    "groups": [
      {
        "n": 1,
        "title": "Isolation Valves",
        "desc": "",
        "cta": "Request a Quotation",
        "items": [
          {
            "name": "Gate Valve",
            "icon": "valve"
          }
        ]
      },
      {
        "n": 2,
        "title": "Check Valves",
        "desc": "",
        "cta": "Request a Quotation",
        "items": [
          {
            "name": "Swing Check Valve",
            "icon": "valve"
          },
          {
            "name": "Wafer Check Valve",
            "icon": "valve"
          },
          {
            "name": "Dual Plate Check Valve",
            "icon": "valve"
          }
        ]
      },
      {
        "n": 3,
        "title": "Air Valves",
        "desc": "",
        "cta": "Request a Quotation",
        "items": [
          {
            "name": "Double-Ball Air Release Valve",
            "icon": "gauge"
          }
        ]
      },
      {
        "n": 4,
        "title": "Special Valves",
        "desc": "",
        "cta": "Request a Quotation",
        "items": [
          {
            "name": "Float Valve",
            "icon": "valve"
          }
        ]
      },
      {
        "n": 5,
        "title": "Strainers",
        "desc": "",
        "cta": "Request a Quotation",
        "items": [
          {
            "name": "Y-Strainer",
            "icon": "grid"
          },
          {
            "name": "Basket Strainer",
            "icon": "grid"
          }
        ]
      },
      {
        "n": 6,
        "title": "Manhole Covers",
        "desc": "",
        "cta": "Request a Quotation",
        "items": [
          {
            "name": "Manhole Covers",
            "icon": "cover"
          }
        ]
      },
      {
        "n": 7,
        "title": "Ductile Iron Fittings",
        "desc": "",
        "cta": "Request a Quotation",
        "items": [
          {
            "name": "Ductile Iron Fittings",
            "icon": "coupling"
          }
        ]
      }
    ],
    "featured": [
      {
        "name": "Isolation Valve",
        "spec": "للحصول على هذا المنتج، الرجاء التواصل مع المورد",
        "icon": "valve",
        "image": "/images/p-isolation-valve.jpg"
      },
      {
        "name": "Isolation Valve — Ref 86",
        "spec": "للحصول على هذا المنتج، الرجاء التواصل مع المورد",
        "icon": "valve",
        "image": "/images/p-isolation-valve-ref-86.jpg"
      },
      {
        "name": "Check Valve",
        "spec": "للحصول على هذا المنتج، الرجاء التواصل مع المورد",
        "icon": "valve",
        "image": "/images/p-check-valve.jpg"
      },
      {
        "name": "Air Valve",
        "spec": "للحصول على هذا المنتج، الرجاء التواصل مع المورد",
        "icon": "gauge",
        "image": "/images/p-air-valve.jpg"
      },
      {
        "name": "Special Valve",
        "spec": "للحصول على هذا المنتج، الرجاء التواصل مع المورد",
        "icon": "valve",
        "image": "/images/p-special-valve.jpg"
      },
      {
        "name": "Strainer",
        "spec": "للحصول على هذا المنتج، الرجاء التواصل مع المورد",
        "icon": "grid",
        "image": "/images/p-strainer.jpg"
      },
      {
        "name": "Manhole Cover",
        "spec": "للحصول على هذا المنتج، الرجاء التواصل مع المورد",
        "icon": "cover",
        "image": "/images/p-manhole-cover.jpg"
      },
      {
        "name": "Ductile Iron Fitting",
        "spec": "للحصول على هذا المنتج، الرجاء التواصل مع المورد",
        "icon": "coupling",
        "image": "/images/p-ductile-iron-fitting.jpg"
      }
    ]
  }
}